app/__init__.py
app/batch_decoder.py
app/camera_recorder.py
app/car_ip.py
app/conftest.py
app/decode_it_all.py
app/fast_decoder.py
app/gui_workers.py
app/main_gui.py
app/plot_hdf5.py
app/vehicle_log_gui.py
app/vehicle_logger_func.py
app/vehicle_logger_logic.py
my_pyqt_app-0.1.dist-info/METADATA
my_pyqt_app-0.1.dist-info/WHEEL
my_pyqt_app-0.1.dist-info/entry_points.txt
my_pyqt_app-0.1.dist-info/top_level.txt
my_pyqt_app-0.1.dist-info/RECORD
